splintershell/__init__.py
splintershell/__main__.py
splintershell/version.py
splintershell/cli/__init__.py
splintershell/cli/core.py
splintershell/cli/encode.py
splintershell/cli/test.py
splintershell/cli/train.py
splintershell/common/__init__.py
splintershell/common/frequency.py
splintershell/encoding/__init__.py
splintershell/encoding/blend.py
splintershell/encoding/schemes/__init__.py
splintershell/encoding/schemes/encoder.py
splintershell/encoding/schemes/xor.py
splintershell/errors/__init__.py
splintershell/errors/arguments.py
splintershell/errors/base.py
splintershell/errors/encoding.py
splintershell/errors/operations.py
splintershell/errors/protocols.py
splintershell/learning/__init__.py
splintershell/learning/model.py
splintershell/protocols/__init__.py
splintershell/protocols/http.py
splintershell/protocols/pcapparser.py
splintershell-0.1.0.dist-info/LICENSE
splintershell-0.1.0.dist-info/METADATA
splintershell-0.1.0.dist-info/WHEEL
splintershell-0.1.0.dist-info/entry_points.txt
splintershell-0.1.0.dist-info/top_level.txt
splintershell-0.1.0.dist-info/RECORD
